csh/__init__.py
csh/cshldap.py
csh/member.py
csh/utils.py
csh/webnews.py
csh-0.2.1.dist-info/top_level.txt
csh-0.2.1.dist-info/METADATA
csh-0.2.1.dist-info/DESCRIPTION.rst
csh-0.2.1.dist-info/metadata.json
csh-0.2.1.dist-info/WHEEL
csh-0.2.1.dist-info/RECORD
