Metadata-Version: 2.0
Name: csh
Version: 0.2.1
Summary: A collection of utilities for interacting with CSH services.
Home-page: https://github.com/gambogi/cshpy
Author: Matt Gambogi
Author-email: gambogi@csh.rit.edu
License: UNKNOWN
Platform: UNKNOWN
Requires-Dist: sasl (==0.1.3)
Requires-Dist: python-ldap (==2.4.17)
Requires-Dist: requests (==2.3.0)
Requires-Dist: wsgiref (==0.1.2)
